hexagdly/__init__.py
hexagdly/hexagdly.py
hexagdly-2.0.2.dist-info/LICENSE
hexagdly-2.0.2.dist-info/METADATA
hexagdly-2.0.2.dist-info/WHEEL
hexagdly-2.0.2.dist-info/top_level.txt
hexagdly-2.0.2.dist-info/RECORD
